{
  "player_white_industry":{
    "type": "PLAYER",
    "factories": [
      {
        "type": "COLLISION",
        "hitShape": "hitshape_white"
      },
      {
        "type": "VELOCITY",
        "velocity": {
          "x": 0,
          "y": 0
        },
        "deltaRot": 0
      },
      {
        "type": "HEALTH",
        "health": 5000,
        "maxHealth": 5000
      },
      {
        "type": "SPRITE",
        "sprite": "white",
        "scale": 4
      },
      {
        "type": "RENDER",
        "visible": true,
        "renderers": [
          {
            "type": "SPRITESHEET"
          },
          {
            "type": "VELOCITY"
          }
        ]
      },
      {
        "type": "MOVE",
        "maxSpeed": 20,
        "turnRate": 0.15,
        "acc": 0.25
      },
      {
        "type": "INPUT",
        "inputType": "PLAYER"
      },
      {
        "type": "DAMAGE"
      },
      {
        "type": "PRIMARY",
        "itemIndustries": [
          "basic_laser_item_industry"
        ]
      },
      {
        "type": "SECONDARY",
        "itemIndustries": [
          "homing_missile_item_industry"
        ]
      },
      {
        "type": "SHIP",
        "itemIndustries": [
          "force_shield_item_industry"
        ]
      },
      {
        "type": "POSITION",
        "coord": {
          "x": 0,
          "y": 0
        },
        "rot": 0
      },
      {
        "type": "DEATH",
        "deathType": "PLAYER"
      },
      {
        "type": "EXPERIENCE",
        "xp": 0,
        "level": 0
      },
      {
        "type": "EFFECT"
      },
      {
        "type": "ACTOR",
        "canShoot": true,
        "canMove": true
      }
    ]
  }
}